reahl/commands/__init__.py
reahl/commands/migrations.py
reahl/commands/prodshell.py
reahl_commands-7.0.3.dist-info/METADATA
reahl_commands-7.0.3.dist-info/WHEEL
reahl_commands-7.0.3.dist-info/entry_points.txt
reahl_commands-7.0.3.dist-info/reahl-component.toml
reahl_commands-7.0.3.dist-info/top_level.txt
reahl_commands-7.0.3.dist-info/RECORD
