Metadata-Version: 2.1
Name: reahl-commands
Version: 7.0.3
Summary: The component framework of Reahl.
Author-email: Iwan Vosloo <iwan@reahl.org>, Craig Sparks <craig@reahl.org>
Classifier: Development Status :: 5 - Production/Stable
Classifier: Intended Audience :: Developers
Classifier: License :: OSI Approved
Classifier: Operating System :: OS Independent
Classifier: Programming Language :: Python :: 3
Classifier: Environment :: Console
Classifier: Topic :: Software Development
Requires-Python: >=3.8
Requires-Dist: reahl-component <7.1,>=7.0
Requires-Dist: importlib-resources ; python_version < "3.9"
